pocketflow/__init__.py
pocketflow/py.typed
pocketflow_agui-0.1.0.dist-info/licenses/LICENSE
pocketflow_agui-0.1.0.dist-info/METADATA
pocketflow_agui-0.1.0.dist-info/WHEEL
pocketflow_agui-0.1.0.dist-info/top_level.txt
pocketflow_agui-0.1.0.dist-info/RECORD
