Metadata-Version: 2.4
Name: pocketflow-agui
Version: 0.1.0
Summary: PocketFlow的AGUI扩展版本 - 支持前端事件回调的轻量级工作流编排框架
Home-page: https://github.com/yourusername/pocketflow-agui
Author: AGUI Team
Author-email: AGUI Team <agui@example.com>
License: MIT
Project-URL: Homepage, https://github.com/yourusername/pocketflow-agui
Project-URL: Repository, https://github.com/yourusername/pocketflow-agui
Project-URL: Issues, https://github.com/yourusername/pocketflow-agui/issues
Project-URL: Documentation, https://github.com/yourusername/pocketflow-agui/blob/main/README.md
Keywords: workflow,orchestration,agui,frontend,events
Classifier: Development Status :: 4 - Beta
Classifier: Intended Audience :: Developers
Classifier: License :: OSI Approved :: MIT License
Classifier: Programming Language :: Python :: 3
Classifier: Programming Language :: Python :: 3.8
Classifier: Programming Language :: Python :: 3.9
Classifier: Programming Language :: Python :: 3.10
Classifier: Programming Language :: Python :: 3.11
Classifier: Programming Language :: Python :: 3.12
Classifier: Topic :: Software Development :: Libraries :: Python Modules
Classifier: Topic :: System :: Distributed Computing
Requires-Python: >=3.8
License-File: LICENSE
Requires-Dist: typing-extensions>=4.0.0; python_version < "3.10"
Provides-Extra: dev
Requires-Dist: pytest>=7.0; extra == "dev"
Requires-Dist: pytest-cov; extra == "dev"
Requires-Dist: pytest-asyncio; extra == "dev"
Requires-Dist: black; extra == "dev"
Requires-Dist: isort; extra == "dev"
Requires-Dist: flake8; extra == "dev"
Requires-Dist: mypy; extra == "dev"
Requires-Dist: pre-commit; extra == "dev"
Dynamic: author
Dynamic: home-page
Dynamic: license-file
Dynamic: requires-python
